README.md
setup.py
horimotemce/__init__.py
horimotemce/horimotemce.py
horimotemce/keys.py
horimotemce.egg-info/PKG-INFO
horimotemce.egg-info/SOURCES.txt
horimotemce.egg-info/dependency_links.txt
horimotemce.egg-info/entry_points.txt
horimotemce.egg-info/requires.txt
horimotemce.egg-info/top_level.txt