Metadata-Version: 2.1
Name: horimotemce
Version: 0.1.0
Summary: Bridge MCE IR remote events to a Horimote client
Home-page: https://github.com/crowbarz/horimotemce
Author: Crowbar Z
Author-email: crowbarz@outlook.com
License: MIT
Keywords: horimote mce
Platform: UNKNOWN
Classifier: Development Status :: 5 - Production/Stable
Classifier: Intended Audience :: Developers
Classifier: Operating System :: OS Independent
Classifier: License :: OSI Approved :: MIT License
Classifier: Programming Language :: Python
Classifier: Programming Language :: Python :: 3.6
Classifier: Programming Language :: Python :: 3.7
Classifier: Topic :: Multimedia
Requires-Python: >=3.6
